dfrun/__init__.py
dfrun/__main__.py
dfrun-0.1.5.dist-info/LICENSE
dfrun-0.1.5.dist-info/METADATA
dfrun-0.1.5.dist-info/WHEEL
dfrun-0.1.5.dist-info/entry_points.txt
dfrun-0.1.5.dist-info/top_level.txt
dfrun-0.1.5.dist-info/RECORD
