Metadata-Version: 2.1
Name: dfrun
Version: 0.1.5
Summary: Code copier for multi experiments
Home-page: UNKNOWN
Author: Rudolfxx
Author-email: mayeoliver@163.com
License: UNKNOWN
Platform: UNKNOWN
Classifier: Programming Language :: Python :: 3
Classifier: License :: OSI Approved :: MIT License
Classifier: Operating System :: OS Independent
